{
  "FR": [
    "BL",
    "FR",
    "GF",
    "GP",
    "MF",
    "MQ",
    "NC",
    "PF",
    "PM",
    "RE",
    "TF",
    "WF",
    "YT"
  ],
  "NL": [
    "AW",
    "BQ",
    "CW",
    "NL",
    "SX"
  ],
  "GB": [
    "AI",
    "BM",
    "FK",
    "GB",
    "GG",
    "GI",
    "GS",
    "IM",
    "IO",
    "JE",
    "KY",
    "MS",
    "PN",
    "SH",
    "TC",
    "VG"
  ],
  "US": [
    "AS",
    "GU",
    "MP",
    "PR",
    "UM",
    "US",
    "VI"
  ],
  "DK": [
    "DK",
    "FO",
    "GL"
  ],
  "NO": [
    "BV",
    "NO",
    "SJ"
  ],
  "FI": [
    "AX",
    "FI"
  ],
  "AU": [
    "AU",
    "CC",
    "CX",
    "HM",
    "NF"
  ],
  "NZ": [
    "NZ",
    "TK"
  ]
}

